{
  "$schema": "http://json-schema.org/draft-07/schema#",
  "$id": "2337c29e-0c25-eb11-82d4-06df8a4a2891",
  "title": "Term Deposit Transaction Agreement Account",
  "description": "",
  "x-version": "1.0.0",
  "x-object-type": "Class",
  "x-super-type": "9fe05cf9-fd60-e911-8237-068e13695e26",
  "x-status": "stable",
  "x-modified-by": null,
  "x-modified-date": "2026-06-16T19:47:23.731Z",
  "x-position": null,
  "type": "object",
  "required": [],
  "properties": {},
  "x-relationships": [
    {
      "id": "42989cb3-0c25-eb11-82d4-06df8a4a2891",
      "target": "9fe05cf9-fd60-e911-8237-068e13695e26",
      "modality": "1:1",
      "required": true,
      "description": "Inherits from Account",
      "x-relationship-type": "generalization",
      "x-status": "stable",
      "x-modified-by": null,
      "x-modified-date": null
    },
    {
      "id": "d2192913-0d25-eb11-82d4-06df8a4a2891",
      "target": "7c9ae6fe-0c25-eb11-82d4-06df8a4a2891",
      "modality": "1:N",
      "required": false,
      "description": "",
      "x-relationship-type": "composition",
      "x-status": "stable",
      "x-modified-by": null,
      "x-modified-date": null
    }
  ],
  "x-enumeration-literals": []
}