{
  "$schema": "http://json-schema.org/draft-07/schema#",
  "$id": "95d7c004-6927-f111-860d-02f56513e735",
  "title": "Compliance Arrangement",
  "description": "Is an Arrangement that governs the legal, regulatory, and policy obligations associated with a financial product",
  "x-version": "1.0.0",
  "x-object-type": "Class",
  "x-super-type": "dd3cc0aa-0a68-e911-8237-06dd5e24f7bc",
  "x-status": "stable",
  "x-modified-by": null,
  "x-modified-date": "2026-06-15T15:59:19.176Z",
  "x-position": null,
  "type": "object",
  "required": [
    "ComplianceAuditFrequency",
    "ComplianceStatus",
    "ComplianceArrangementType",
    "ComplianceRegulatoryScope",
    "ComplianceRiskClassification",
    "ComplianceMonitoringFrequency",
    "ComplianceCustomerApplicabilityType",
    "ComplianceTransactionApplicabilityType",
    "ComplianceReviewDate",
    "ComplianceLastUpdatedDate"
  ],
  "properties": {
    "ComplianceAuditFrequency": {
      "type": "string",
      "description": "How often the arrangement is reviewed",
      "x-status": "stable",
      "x-modified-by": null,
      "x-modified-date": "2026-06-15T15:59:19.185Z",
      "x-previous-value": null,
      "x-multi-valued": false,
      "x-is-unique": true,
      "x-min-occurs": 1,
      "x-max-occurs": 1,
      "x-attr-type": "Frequency",
      "x-related-bo-id": "10ff97d4-70fb-eb11-833a-069538764ea9",
      "x-related-bo-name": "Frequency"
    },
    "ComplianceStatus": {
      "type": "string",
      "description": "Indicates whether a customer, transaction, or process meets regulatory and internal compliance requirements.",
      "x-status": "stable",
      "x-modified-by": null,
      "x-modified-date": "2026-06-15T15:59:19.185Z",
      "x-previous-value": null,
      "x-multi-valued": false,
      "x-is-unique": true,
      "x-min-occurs": 1,
      "x-max-occurs": 1,
      "x-attr-type": "Status",
      "x-related-bo-id": "c7cfae85-cde3-ea11-82b8-069eade4826b",
      "x-related-bo-name": "Status"
    },
    "ComplianceArrangementType": {
      "type": "string",
      "description": "Compliance Arrangement Types are structured categories of contractual and operational rules that define how compliance is ensured, monitored, and enforced across different dimensions.",
      "x-status": "stable",
      "x-modified-by": null,
      "x-modified-date": "2026-06-15T15:59:19.185Z",
      "x-previous-value": null,
      "x-multi-valued": false,
      "x-is-unique": true,
      "x-min-occurs": 1,
      "x-max-occurs": 1,
      "x-attr-type": "ComplianceArrangementTypeValues",
      "x-related-bo-id": "10de012a-8627-f111-860d-02f56513e735",
      "x-related-bo-name": "ComplianceArrangementTypeValues"
    },
    "ComplianceRegulatoryScope": {
      "type": "string",
      "description": "Identifies the laws, regulations, or standards the arrangement must comply with.\r\n\r\nComment:\r\nExample: GDPR, FATCA, CRS, local AML laws.",
      "x-status": "stable",
      "x-modified-by": null,
      "x-modified-date": "2026-06-15T15:59:19.185Z",
      "x-previous-value": null,
      "x-multi-valued": false,
      "x-is-unique": true,
      "x-min-occurs": 1,
      "x-max-occurs": 1,
      "x-attr-type": "Text",
      "x-related-bo-id": "98855d84-16ee-eb11-8336-0692f5211cfd",
      "x-related-bo-name": "Text"
    },
    "ComplianceRiskClassification": {
      "type": "string",
      "description": "Categorizes arrangement risk level (e.g. Low, Medium, High, Critical)",
      "x-status": "stable",
      "x-modified-by": null,
      "x-modified-date": "2026-06-15T15:59:19.185Z",
      "x-previous-value": null,
      "x-multi-valued": false,
      "x-is-unique": true,
      "x-min-occurs": 1,
      "x-max-occurs": 1,
      "x-attr-type": "Text",
      "x-related-bo-id": "98855d84-16ee-eb11-8336-0692f5211cfd",
      "x-related-bo-name": "Text"
    },
    "ComplianceMonitoringFrequency": {
      "type": "string",
      "description": "Frequency of monitoring or reporting",
      "x-status": "stable",
      "x-modified-by": null,
      "x-modified-date": "2026-06-15T15:59:19.185Z",
      "x-previous-value": null,
      "x-multi-valued": false,
      "x-is-unique": true,
      "x-min-occurs": 1,
      "x-max-occurs": 1,
      "x-attr-type": "Frequency",
      "x-related-bo-id": "10ff97d4-70fb-eb11-833a-069538764ea9",
      "x-related-bo-name": "Frequency"
    },
    "ComplianceCustomerApplicabilityType": {
      "type": "string",
      "description": "Specifies the types of customers to which a compliance arrangement applies.",
      "x-status": "stable",
      "x-modified-by": null,
      "x-modified-date": "2026-06-15T15:59:19.185Z",
      "x-previous-value": null,
      "x-multi-valued": false,
      "x-is-unique": true,
      "x-min-occurs": 1,
      "x-max-occurs": 1,
      "x-attr-type": "string"
    },
    "ComplianceTransactionApplicabilityType": {
      "type": "string",
      "description": "Specifies the types of transactions to which a compliance arrangement applies.",
      "x-status": "stable",
      "x-modified-by": null,
      "x-modified-date": "2026-06-15T15:59:19.185Z",
      "x-previous-value": null,
      "x-multi-valued": false,
      "x-is-unique": true,
      "x-min-occurs": 1,
      "x-max-occurs": 1,
      "x-attr-type": "ComplianceTransactionApplicabilityTypeValues",
      "x-related-bo-id": "f62bbb97-8b27-f111-860d-02f56513e735",
      "x-related-bo-name": "ComplianceTransactionApplicabilityTypeValues"
    },
    "ComplianceReviewDate": {
      "type": "string",
      "description": "Scheduled date for reviewing or auditing the arrangement.\r\n\r\nComment:\r\nExample: 2026-06-30  mid-year internal audit for AML rules.",
      "x-status": "stable",
      "x-modified-by": null,
      "x-modified-date": "2026-06-15T15:59:19.185Z",
      "x-previous-value": null,
      "x-multi-valued": false,
      "x-is-unique": true,
      "x-min-occurs": 1,
      "x-max-occurs": 1,
      "x-attr-type": "DateTime",
      "x-related-bo-id": "b41f5ecc-fbed-eb11-8336-0692f5211cfd",
      "x-related-bo-name": "DateTime"
    },
    "ComplianceLastUpdatedDate": {
      "type": "string",
      "description": "The date when the arrangement or its rules were last modified.\r\n\r\nComment:\r\nExample: 2026-03-01  AML transaction monitoring rules updated.",
      "x-status": "stable",
      "x-modified-by": null,
      "x-modified-date": "2026-06-15T15:59:19.185Z",
      "x-previous-value": null,
      "x-multi-valued": false,
      "x-is-unique": true,
      "x-min-occurs": 1,
      "x-max-occurs": 1,
      "x-attr-type": "DateTime",
      "x-related-bo-id": "b41f5ecc-fbed-eb11-8336-0692f5211cfd",
      "x-related-bo-name": "DateTime"
    }
  },
  "x-relationships": [
    {
      "id": "97e01838-6927-f111-860d-02f56513e735",
      "target": "dd3cc0aa-0a68-e911-8237-06dd5e24f7bc",
      "modality": "1:1",
      "required": true,
      "description": "Inherits from Arrangement",
      "x-relationship-type": "generalization",
      "x-status": "stable",
      "x-modified-by": null,
      "x-modified-date": null
    },
    {
      "id": "96c58376-6927-f111-860d-02f56513e735",
      "target": "7317a96e-6927-f111-860d-02f56513e735",
      "modality": "1:N",
      "required": false,
      "description": "",
      "x-relationship-type": "association",
      "x-status": "stable",
      "x-modified-by": null,
      "x-modified-date": null
    },
    {
      "id": "56505562-6927-f111-860d-02f56513e735",
      "target": "eca3884c-6927-f111-860d-02f56513e735",
      "modality": "1:N",
      "required": false,
      "description": "",
      "x-relationship-type": "association",
      "x-status": "stable",
      "x-modified-by": null,
      "x-modified-date": null
    }
  ],
  "x-enumeration-literals": []
}