{
  "$schema": "http://json-schema.org/draft-07/schema#",
  "$id": "caceab19-490b-f111-8602-0ad4a82ce56b",
  "title": "Burn Involvement",
  "description": "Burn Involvement refers to the participation or role of parties in the process of using, redeeming, or consuming earned incentives under a burn arrangement.",
  "x-version": "1.0.0",
  "x-object-type": "Class",
  "x-super-type": null,
  "x-status": "stable",
  "x-modified-by": null,
  "x-modified-date": "2026-06-15T15:59:19.176Z",
  "x-position": null,
  "type": "object",
  "required": [
    "BurnInvolvementType"
  ],
  "properties": {
    "BurnInvolvementType": {
      "type": "string",
      "description": "A Burn Involvement Type is the classification of the role a party plays in the redemption or usage of incentives under a burn arrangement.",
      "x-status": "stable",
      "x-modified-by": null,
      "x-modified-date": "2026-06-15T15:59:19.185Z",
      "x-previous-value": null,
      "x-multi-valued": false,
      "x-is-unique": true,
      "x-min-occurs": 1,
      "x-max-occurs": 1,
      "x-attr-type": "BurnInvolvementTypeValues",
      "x-related-bo-id": "65a4daaf-490b-f111-8602-0ad4a82ce56b",
      "x-related-bo-name": "BurnInvolvementTypeValues"
    }
  },
  "x-relationships": [],
  "x-enumeration-literals": []
}